cai_causal_impact/__init__.py
cai_causal_impact-0.0.0.dist-info/WHEEL
cai_causal_impact-0.0.0.dist-info/METADATA
cai_causal_impact-0.0.0.dist-info/RECORD
